instaloaderhamdambek.py
instaloaderhamdambek-0.0.1.dist-info/WHEEL
instaloaderhamdambek-0.0.1.dist-info/METADATA
instaloaderhamdambek-0.0.1.dist-info/RECORD
